readycheck.py
readycheck-1.0.1.dist-info/LICENSE
readycheck-1.0.1.dist-info/METADATA
readycheck-1.0.1.dist-info/WHEEL
readycheck-1.0.1.dist-info/top_level.txt
readycheck-1.0.1.dist-info/RECORD
