Metadata-Version: 2.1
Name: readycheck
Version: 1.0.1
Summary: Run custom checks on classes attributes when accessing them
Home-page: https://github.com/loic-simon/readycheck
Author: Loïc Simon
Author-email: loic.simon@espci.org
License: UNKNOWN
Platform: UNKNOWN
Classifier: Development Status :: 5 - Production/Stable
Classifier: Intended Audience :: Developers
Classifier: Programming Language :: Python :: 3.10
Classifier: License :: OSI Approved :: MIT License
Classifier: Operating System :: OS Independent
Requires-Python: >=3.10
License-File: LICENSE
